deepseek_mcp_client/__init__.py
deepseek_mcp_client/client/__init__.py
deepseek_mcp_client/client/deepseek_client.py
deepseek_mcp_client/handlers/__init__.py
deepseek_mcp_client/handlers/message_handler.py
deepseek_mcp_client/models/__init__.py
deepseek_mcp_client/models/client_result.py
deepseek_mcp_client/models/server_config.py
deepseek_mcp_client/utils/__init__.py
deepseek_mcp_client/utils/logging_config.py
example_stdio/__init__.py
example_stdio/example_stdio.py
deepseek_mcp_client-2.0.0.dist-info/METADATA
deepseek_mcp_client-2.0.0.dist-info/WHEEL
deepseek_mcp_client-2.0.0.dist-info/top_level.txt
deepseek_mcp_client-2.0.0.dist-info/RECORD
