Metadata-Version: 2.4
Name: deepseek-mcp-client
Version: 2.0.0
Summary: Cliente para conectar modelos DeepSeek con servidores MCP
Home-page: https://github.com/CarlosMaroRuiz/deepseek-mcp-client
Author: Carlos Ruiz
Author-email: Carlos Ruiz <car06ma15@gmail.com>
Maintainer-email: Carlos Ruiz <car06ma15@gmail.com>
License: MIT
Project-URL: Homepage, https://github.com/CarlosMaroRuiz/deepseek-mcp-client
Project-URL: Repository, https://github.com/CarlosMaroRuiz/deepseek-mcp-client
Project-URL: Documentation, https://github.com/CarlosMaroRuiz/deepseek-mcp-client#readme
Project-URL: Bug Tracker, https://github.com/CarlosMaroRuiz/deepseek-mcp-client/issues
Keywords: deepseek,mcp,client,ai,llm,model context protocol,tools,agent
Classifier: Development Status :: 5 - Production/Stable
Classifier: Intended Audience :: Developers
Classifier: License :: OSI Approved :: MIT License
Classifier: Operating System :: OS Independent
Classifier: Programming Language :: Python :: 3
Classifier: Programming Language :: Python :: 3.8
Classifier: Programming Language :: Python :: 3.9
Classifier: Programming Language :: Python :: 3.10
Classifier: Programming Language :: Python :: 3.11
Classifier: Programming Language :: Python :: 3.12
Classifier: Topic :: Software Development :: Libraries :: Python Modules
Classifier: Topic :: Scientific/Engineering :: Artificial Intelligence
Requires-Python: >=3.8
Requires-Dist: python-dotenv>=1.0.0
Requires-Dist: requests>=2.31.0
Requires-Dist: mcp>=1.0.0
Requires-Dist: uvicorn>=0.32.1
Requires-Dist: openai>=1.67.0
Requires-Dist: httpx
Requires-Dist: fastmcp
Provides-Extra: dev
Requires-Dist: pytest>=6.0; extra == "dev"
Requires-Dist: black>=22.0; extra == "dev"
Requires-Dist: flake8>=4.0; extra == "dev"
Requires-Dist: isort>=5.0; extra == "dev"
Provides-Extra: docs
Requires-Dist: sphinx>=4.0; extra == "docs"
Requires-Dist: sphinx-rtd-theme>=1.0; extra == "docs"
Provides-Extra: test
Requires-Dist: pytest>=6.0; extra == "test"
Requires-Dist: pytest-asyncio>=0.20; extra == "test"
Requires-Dist: pytest-cov>=3.0; extra == "test"
Dynamic: author
Dynamic: home-page
Dynamic: requires-python
